xbxdata/xbxdata.py
xtquant/__init__.py
xtquant/datacenter.cp310-win_amd64.pyd
xtquant/datacenter.cp311-win_amd64.pyd
xtquant/datacenter.cp312-win_amd64.pyd
xtquant/datacenter.cp36-win_amd64.pyd
xtquant/datacenter.cp37-win_amd64.pyd
xtquant/datacenter.cp38-win_amd64.pyd
xtquant/datacenter.cp39-win_amd64.pyd
xtquant/libeay32.dll
xtquant/log4cxx.dll
xtquant/msvcp140.dll
xtquant/ssleay32.dll
xtquant/vcruntime140.dll
xtquant/xtconn.py
xtquant/xtconstant.py
xtquant/xtdata.ini
xtquant/xtdata.log4cxx
xtquant/xtdata.py
xtquant/xtdata_config.py
xtquant/xtdatacenter.py
xtquant/xtextend.py
xtquant/xtpythonclient.cp310-win_amd64.pyd
xtquant/xtpythonclient.cp311-win_amd64.pyd
xtquant/xtpythonclient.cp312-win_amd64.pyd
xtquant/xtpythonclient.cp36-win_amd64.pyd
xtquant/xtpythonclient.cp37-win_amd64.pyd
xtquant/xtpythonclient.cp38-win_amd64.pyd
xtquant/xtpythonclient.cp39-win_amd64.pyd
xtquant/xtstocktype.py
xtquant/xttools.py
xtquant/xttrader.py
xtquant/xttype.py
xtquant/xtutil.py
xtquant/xtview.py
xtquant/config/MarketTime.ini
xtquant/config/StockInfo.lua
xtquant/config/captial_structure_1.ini
xtquant/config/cashflow_new_1.ini
xtquant/config/config.lua
xtquant/config/configHelper.lua
xtquant/config/env.lua
xtquant/config/metaInfo.json
xtquant/config/pershare_new.ini
xtquant/config/sharebalance_new_1.ini
xtquant/config/shareholder_new_1.ini
xtquant/config/shareincome_new_1.ini
xtquant/config/table2json.lua
xtquant/config/top10holder_new_1.ini
xtquant/config/tradeTime.txt
xtquant/config/xtquantservice.log4cxx
xtquant/config/xtquantservice.lua
xtquant/config/xtquoterconfig.xml
xtquant/config/xtstocktype.lua
xtquant/config/user/root2/lua/ConstFunc.lua
xtquant/config/user/root2/lua/FunIndex.lua
xtquant/config/user/root2/lua/FunLogic.lua
xtquant/config/user/root2/lua/FunMath.lua
xtquant/config/user/root2/lua/FunOther.lua
xtquant/config/user/root2/lua/FunRef.lua
xtquant/config/user/root2/lua/FunStatistic.lua
xtquant/config/user/root2/lua/FunString.lua
xbx_py11-0.1.19.dist-info/METADATA
xbx_py11-0.1.19.dist-info/WHEEL
xbx_py11-0.1.19.dist-info/top_level.txt
xbx_py11-0.1.19.dist-info/RECORD
