Metadata-Version: 2.4
Name: xbx-py11
Version: 0.1.19
Summary: xbx-py11
Author: xbx-py11
Requires-Dist: ccxt==4.5.22
Requires-Dist: dataframe_image==0.2.4
Requires-Dist: DrissionPage==4.1.0.14
Requires-Dist: lxml==5.3.0
Requires-Dist: ntplib==0.4.0
Requires-Dist: httpx==0.27.2
Requires-Dist: bs4==0.0.2
Requires-Dist: scipy==1.14.1
Requires-Dist: tabulate==0.9.0
Requires-Dist: dash==2.18.1
Requires-Dist: dash-iconify==0.1.2
Requires-Dist: dash-mantine-components==0.14.5
Requires-Dist: scikit-learn==1.5.2
Requires-Dist: py-mini-racer==0.6.0
Requires-Dist: psutil==6.0.0
Requires-Dist: py7zr==0.22.0
Requires-Dist: rarfile==4.2
Requires-Dist: matplotlib==3.9.2
Requires-Dist: joblib==1.4.2
Requires-Dist: numpy==2.0.2
Requires-Dist: pandas==2.2.3
Requires-Dist: requests==2.32.3
Requires-Dist: PyExecJS==1.5.1
Requires-Dist: tqdm==4.66.5
Requires-Dist: plotly==5.24.1
Requires-Dist: pyarrow==17.0.0
Requires-Dist: retrying==1.3.4
Requires-Dist: colorama==0.4.6
Requires-Dist: seaborn==0.13.2
Requires-Dist: numba==0.60.0
Requires-Dist: openpyxl==3.1.5
Requires-Dist: unlock_joblib_tasks==1.3
Requires-Dist: zstandard==0.23.0
Requires-Dist: unlock-processpool-win==2.1.0
Requires-Dist: schedule==1.2.2
Requires-Dist: xlrd==2.0.1
Requires-Dist: fastapi==0.115.12
Requires-Dist: uvicorn==0.34.2
Requires-Dist: python-jose==3.5.0
Requires-Dist: python-multipart==0.0.20
Requires-Dist: pyotp==2.9.0
Requires-Dist: sqlalchemy==2.0.41
Requires-Dist: pycryptodome==3.21.0
Dynamic: author
Dynamic: requires-dist
Dynamic: summary
